README.txt
setup.py
edopkg/__init__.py
edopkg/cmdparser.py
edopkg/config.py
edopkg/env.py
edopkg/main.py
edopkg/package.py
edopkg/utils.py
edopkg.egg-info/PKG-INFO
edopkg.egg-info/SOURCES.txt
edopkg.egg-info/dependency_links.txt
edopkg.egg-info/entry_points.txt
edopkg.egg-info/not-zip-safe
edopkg.egg-info/requires.txt
edopkg.egg-info/top_level.txt
edopkg/pyaml/__init__.py
edopkg/pyaml/__main__.py