Metadata-Version: 1.0
Name: edopkg
Version: 0.1.14
Summary: Easydo Package Syncer
Home-page: http://everydo.com/
Author: xiehaiyang
Author-email: service@everydo.com
License: UNKNOWN
Platform: UNKNOWN
